README.rst
setup.py
iaar_gen_news_process/__init__.py
iaar_gen_news_process/defaults.py
iaar_gen_news_process/exceptions.py
iaar_gen_news_process/utils.py
iaar_gen_news_process.egg-info/PKG-INFO
iaar_gen_news_process.egg-info/SOURCES.txt
iaar_gen_news_process.egg-info/dependency_links.txt
iaar_gen_news_process.egg-info/top_level.txt
iaar_gen_news_process.egg-info/zip-safe
iaar_gen_news_process/extractor/AuthorExtractor.py
iaar_gen_news_process/extractor/ContentExtractor.py
iaar_gen_news_process/extractor/ListExtractor.py
iaar_gen_news_process/extractor/MetaExtractor.py
iaar_gen_news_process/extractor/TimeExtractor.py
iaar_gen_news_process/extractor/TitleExtractor.py
iaar_gen_news_process/extractor/__init__.py