Metadata-Version: 1.1
Name: iaar-gen-news-process
Version: 1.0.4
Summary: this is a tool package for iaar. 日期提取优化
Home-page: https://github.com/pypa/sampleproject
Author: Gie
Author-email: 593443714@qq.com
License: MIT
Keywords: iaar utils
Platform: UNKNOWN
Classifier: License :: OSI Approved :: MIT License
Classifier: Programming Language :: Python
Classifier: Intended Audience :: Developers
Classifier: Operating System :: OS Independent
